{
  "page_number": 74,
  "hizb_number": "8",
  "is_intro": "",
  "page_surah_title": "سورة آل عمران",
  "page_surah_title_lt": "Al-Imraan",
  "page_size": "M",
  "lines": [
    {
      "line_id": 0,
      "line_number": 1,
      "is_surah_title": "",
      "surah_title": "ءَالِ عِمْرَانَ",
      "surah_title_ar": "آل عمران",
      "surah_title_lt": "Al-Imraan",
      "starts_with_verse_number": "",
      "words": [
        {
          "id": "9673",
          "surah_order": "3273",
          "quran_order": "9423",
          "text": "بِـمَـا",
          "surah_number": "3",
          "hizb_number": "8",
          "tomon_number": "3",
          "line_order": "1",
          "verse_order": "10",
          "is_last_word": "",
          "is_first_tomon": "",
          "verse": {
            "verse_number": "188",
            "next_verse": "189",
            "previous_verse": "187",
            "sajda": "",
            "is_last_verse": "",
            "is_number_linebreak": "",
            "wakf_end": "",
            "word_start": "9414",
            "word_stop": "9433"
          }
        },
        {
          "id": "9677",
          "surah_order": "3274",
          "quran_order": "9424",
          "text": "لَـمْ",
          "surah_number": "3",
          "hizb_number": "8",
          "tomon_number": "3",
          "line_order": "2",
          "verse_order": "11",
          "is_last_word": "",
          "is_first_tomon": "",
          "verse": {
            "verse_number": "188",
            "next_verse": "189",
            "previous_verse": "187",
            "sajda": "",
            "is_last_verse": "",
            "is_number_linebreak": "",
            "wakf_end": "",
            "word_start": "9414",
            "word_stop": "9433"
          }
        },
        {
          "id": "9679",
          "surah_order": "3275",
          "quran_order": "9425",
          "text": "يَـفْـعَـلُـواْ",
          "surah_number": "3",
          "hizb_number": "8",
          "tomon_number": "3",
          "line_order": "3",
          "verse_order": "12",
          "is_last_word": "",
          "is_first_tomon": "",
          "verse": {
            "verse_number": "188",
            "next_verse": "189",
            "previous_verse": "187",
            "sajda": "",
            "is_last_verse": "",
            "is_number_linebreak": "",
            "wakf_end": "",
            "word_start": "9414",
            "word_stop": "9433"
          }
        },
        {
          "id": "9684",
          "surah_order": "3276",
          "quran_order": "9426",
          "text": "فَـلاَ",
          "surah_number": "3",
          "hizb_number": "8",
          "tomon_number": "3",
          "line_order": "4",
          "verse_order": "13",
          "is_last_word": "",
          "is_first_tomon": "",
          "verse": {
            "verse_number": "188",
            "next_verse": "189",
            "previous_verse": "187",
            "sajda": "",
            "is_last_verse": "",
            "is_number_linebreak": "",
            "wakf_end": "",
            "word_start": "9414",
            "word_stop": "9433"
          }
        },
        {
          "id": "9689",
          "surah_order": "3277",
          "quran_order": "9427",
          "text": "تَحْـسِـبَنَّـهُـم",
          "surah_number": "3",
          "hizb_number": "8",
          "tomon_number": "3",
          "line_order": "5",
          "verse_order": "14",
          "is_last_word": "",
          "is_first_tomon": "",
          "verse": {
            "verse_number": "188",
            "next_verse": "189",
            "previous_verse": "187",
            "sajda": "",
            "is_last_verse": "",
            "is_number_linebreak": "",
            "wakf_end": "",
            "word_start": "9414",
            "word_stop": "9433"
          }
        },
        {
          "id": "9695",
          "surah_order": "3278",
          "quran_order": "9428",
          "text": "بِمَفَازَةٍ",
          "surah_number": "3",
          "hizb_number": "8",
          "tomon_number": "3",
          "line_order": "6",
          "verse_order": "15",
          "is_last_word": "",
          "is_first_tomon": "",
          "verse": {
            "verse_number": "188",
            "next_verse": "189",
            "previous_verse": "187",
            "sajda": "",
            "is_last_verse": "",
            "is_number_linebreak": "",
            "wakf_end": "",
            "word_start": "9414",
            "word_stop": "9433"
          }
        },
        {
          "id": "9698",
          "surah_order": "3279",
          "quran_order": "9429",
          "text": "مِّـنَ",
          "surah_number": "3",
          "hizb_number": "8",
          "tomon_number": "3",
          "line_order": "7",
          "verse_order": "16",
          "is_last_word": "",
          "is_first_tomon": "",
          "verse": {
            "verse_number": "188",
            "next_verse": "189",
            "previous_verse": "187",
            "sajda": "",
            "is_last_verse": "",
            "is_number_linebreak": "",
            "wakf_end": "",
            "word_start": "9414",
            "word_stop": "9433"
          }
        },
        {
          "id": "9701",
          "surah_order": "3280",
          "quran_order": "9430",
          "text": "۰لْعَذَابِؐ",
          "surah_number": "3",
          "hizb_number": "8",
          "tomon_number": "3",
          "line_order": "8",
          "verse_order": "17",
          "is_last_word": "",
          "is_first_tomon": "",
          "verse": {
            "verse_number": "188",
            "next_verse": "189",
            "previous_verse": "187",
            "sajda": "",
            "is_last_verse": "",
            "is_number_linebreak": "",
            "wakf_end": "",
            "word_start": "9414",
            "word_stop": "9433"
          }
        },
        {
          "id": "9704",
          "surah_order": "3281",
          "quran_order": "9431",
          "text": "وَلَهُمْ",
          "surah_number": "3",
          "hizb_number": "8",
          "tomon_number": "3",
          "line_order": "9",
          "verse_order": "18",
          "is_last_word": "",
          "is_first_tomon": "",
          "verse": {
            "verse_number": "188",
            "next_verse": "189",
            "previous_verse": "187",
            "sajda": "",
            "is_last_verse": "",
            "is_number_linebreak": "",
            "wakf_end": "",
            "word_start": "9414",
            "word_stop": "9433"
          }
        }
      ]
    },
    {
      "line_id": 1,
      "line_number": 2,
      "is_surah_title": "",
      "surah_title": "ءَالِ عِمْرَانَ",
      "surah_title_ar": "آل عمران",
      "surah_title_lt": "Al-Imraan",
      "starts_with_verse_number": "",
      "words": [
        {
          "id": "9712",
          "surah_order": "3282",
          "quran_order": "9432",
          "text": "عَذَاببب٘",
          "surah_number": "3",
          "hizb_number": "8",
          "tomon_number": "3",
          "line_order": "1",
          "verse_order": "19",
          "is_last_word": "",
          "is_first_tomon": "",
          "verse": {
            "verse_number": "188",
            "next_verse": "189",
            "previous_verse": "187",
            "sajda": "",
            "is_last_verse": "",
            "is_number_linebreak": "",
            "wakf_end": "",
            "word_start": "9414",
            "word_stop": "9433"
          }
        },
        {
          "id": "9716",
          "surah_order": "3283",
          "quran_order": "9433",
          "text": "اَلِـيـمٌؐ",
          "surah_number": "3",
          "hizb_number": "8",
          "tomon_number": "3",
          "line_order": "2",
          "verse_order": "20",
          "is_last_word": "1",
          "is_first_tomon": "",
          "verse": {
            "verse_number": "188",
            "next_verse": "189",
            "previous_verse": "187",
            "sajda": "",
            "is_last_verse": "",
            "is_number_linebreak": "",
            "wakf_end": "",
            "word_start": "9414",
            "word_stop": "9433"
          }
        },
        {
          "id": "9727",
          "surah_order": "3284",
          "quran_order": "9434",
          "text": "وَلِلهِ",
          "surah_number": "3",
          "hizb_number": "8",
          "tomon_number": "3",
          "line_order": "3",
          "verse_order": "1",
          "is_last_word": "",
          "is_first_tomon": "",
          "verse": {
            "verse_number": "189",
            "next_verse": "190",
            "previous_verse": "188",
            "sajda": "",
            "is_last_verse": "",
            "is_number_linebreak": "",
            "wakf_end": "",
            "word_start": "9434",
            "word_stop": "9442"
          }
        },
        {
          "id": "9731",
          "surah_order": "3285",
          "quran_order": "9435",
          "text": "مُـلْـكُ",
          "surah_number": "3",
          "hizb_number": "8",
          "tomon_number": "3",
          "line_order": "4",
          "verse_order": "2",
          "is_last_word": "",
          "is_first_tomon": "",
          "verse": {
            "verse_number": "189",
            "next_verse": "190",
            "previous_verse": "188",
            "sajda": "",
            "is_last_verse": "",
            "is_number_linebreak": "",
            "wakf_end": "",
            "word_start": "9434",
            "word_stop": "9442"
          }
        },
        {
          "id": "9732",
          "surah_order": "3287",
          "quran_order": "9436",
          "text": "۴لـسَّـمَـٰـوَ؛تتتِ",
          "surah_number": "3",
          "hizb_number": "8",
          "tomon_number": "3",
          "line_order": "5",
          "verse_order": "3",
          "is_last_word": "",
          "is_first_tomon": "",
          "verse": {
            "verse_number": "189",
            "next_verse": "190",
            "previous_verse": "188",
            "sajda": "",
            "is_last_verse": "",
            "is_number_linebreak": "",
            "wakf_end": "",
            "word_start": "9434",
            "word_stop": "9442"
          }
        },
        {
          "id": "9745",
          "surah_order": "3288",
          "quran_order": "9437",
          "text": "وَالاَرْضِؐ",
          "surah_number": "3",
          "hizb_number": "8",
          "tomon_number": "3",
          "line_order": "6",
          "verse_order": "4",
          "is_last_word": "",
          "is_first_tomon": "",
          "verse": {
            "verse_number": "189",
            "next_verse": "190",
            "previous_verse": "188",
            "sajda": "",
            "is_last_verse": "",
            "is_number_linebreak": "",
            "wakf_end": "",
            "word_start": "9434",
            "word_stop": "9442"
          }
        },
        {
          "id": "9761",
          "surah_order": "3289",
          "quran_order": "9438",
          "text": "وَاللَّهُ",
          "surah_number": "3",
          "hizb_number": "8",
          "tomon_number": "3",
          "line_order": "7",
          "verse_order": "5",
          "is_last_word": "",
          "is_first_tomon": "",
          "verse": {
            "verse_number": "189",
            "next_verse": "190",
            "previous_verse": "188",
            "sajda": "",
            "is_last_verse": "",
            "is_number_linebreak": "",
            "wakf_end": "",
            "word_start": "9434",
            "word_stop": "9442"
          }
        },
        {
          "id": "9766",
          "surah_order": "3290",
          "quran_order": "9439",
          "text": "عَلَيٰ",
          "surah_number": "3",
          "hizb_number": "8",
          "tomon_number": "3",
          "line_order": "8",
          "verse_order": "6",
          "is_last_word": "",
          "is_first_tomon": "",
          "verse": {
            "verse_number": "189",
            "next_verse": "190",
            "previous_verse": "188",
            "sajda": "",
            "is_last_verse": "",
            "is_number_linebreak": "",
            "wakf_end": "",
            "word_start": "9434",
            "word_stop": "9442"
          }
        }
      ]
    },
    {
      "line_id": 2,
      "line_number": 3,
      "is_surah_title": "",
      "surah_title": "ءَالِ عِمْرَانَ",
      "surah_title_ar": "آل عمران",
      "surah_title_lt": "Al-Imraan",
      "starts_with_verse_number": "",
      "words": [
        {
          "id": "9781",
          "surah_order": "3286",
          "quran_order": "9440",
          "text": "كُـلِّ",
          "surah_number": "3",
          "hizb_number": "8",
          "tomon_number": "3",
          "line_order": "1",
          "verse_order": "2",
          "is_last_word": "",
          "is_first_tomon": "",
          "verse": {
            "verse_number": "189",
            "next_verse": "190",
            "previous_verse": "188",
            "sajda": "",
            "is_last_verse": "",
            "is_number_linebreak": "",
            "wakf_end": "",
            "word_start": "9434",
            "word_stop": "9442"
          }
        },
        {
          "id": "9793",
          "surah_order": "3291",
          "quran_order": "9441",
          "text": "شَيْءٍ",
          "surah_number": "3",
          "hizb_number": "8",
          "tomon_number": "3",
          "line_order": "2",
          "verse_order": "8",
          "is_last_word": "",
          "is_first_tomon": "",
          "verse": {
            "verse_number": "189",
            "next_verse": "190",
            "previous_verse": "188",
            "sajda": "",
            "is_last_verse": "",
            "is_number_linebreak": "",
            "wakf_end": "",
            "word_start": "9434",
            "word_stop": "9442"
          }
        },
        {
          "id": "9824",
          "surah_order": "3292",
          "quran_order": "9442",
          "text": "قَـدِيـر٘ؐ",
          "surah_number": "3",
          "hizb_number": "8",
          "tomon_number": "3",
          "line_order": "3",
          "verse_order": "9",
          "is_last_word": "1",
          "is_first_tomon": "",
          "verse": {
            "verse_number": "189",
            "next_verse": "190",
            "previous_verse": "188",
            "sajda": "",
            "is_last_verse": "",
            "is_number_linebreak": "",
            "wakf_end": "",
            "word_start": "9434",
            "word_stop": "9442"
          }
        },
        {
          "id": "9842",
          "surah_order": "3293",
          "quran_order": "9443",
          "text": "اِنَّ",
          "surah_number": "3",
          "hizb_number": "8",
          "tomon_number": "3",
          "line_order": "4",
          "verse_order": "1",
          "is_last_word": "",
          "is_first_tomon": "",
          "verse": {
            "verse_number": "190",
            "next_verse": "191",
            "previous_verse": "189",
            "sajda": "",
            "is_last_verse": "",
            "is_number_linebreak": "",
            "wakf_end": "",
            "word_start": "9443",
            "word_stop": "9465"
          }
        },
        {
          "id": "9900",
          "surah_order": "3294",
          "quran_order": "9444",
          "text": "فِى",
          "surah_number": "3",
          "hizb_number": "8",
          "tomon_number": "3",
          "line_order": "5",
          "verse_order": "2",
          "is_last_word": "",
          "is_first_tomon": "",
          "verse": {
            "verse_number": "190",
            "next_verse": "191",
            "previous_verse": "189",
            "sajda": "",
            "is_last_verse": "",
            "is_number_linebreak": "",
            "wakf_end": "",
            "word_start": "9443",
            "word_stop": "9465"
          }
        },
        {
          "id": "9904",
          "surah_order": "3295",
          "quran_order": "9445",
          "text": "خَلْقِ",
          "surah_number": "3",
          "hizb_number": "8",
          "tomon_number": "3",
          "line_order": "6",
          "verse_order": "3",
          "is_last_word": "",
          "is_first_tomon": "",
          "verse": {
            "verse_number": "190",
            "next_verse": "191",
            "previous_verse": "189",
            "sajda": "",
            "is_last_verse": "",
            "is_number_linebreak": "",
            "wakf_end": "",
            "word_start": "9443",
            "word_stop": "9465"
          }
        },
        {
          "id": "9908",
          "surah_order": "3296",
          "quran_order": "9446",
          "text": "۱لسَّمَــٰوَ؛تتتِ",
          "surah_number": "3",
          "hizb_number": "8",
          "tomon_number": "3",
          "line_order": "7",
          "verse_order": "4",
          "is_last_word": "",
          "is_first_tomon": "",
          "verse": {
            "verse_number": "190",
            "next_verse": "191",
            "previous_verse": "189",
            "sajda": "",
            "is_last_verse": "",
            "is_number_linebreak": "",
            "wakf_end": "",
            "word_start": "9443",
            "word_stop": "9465"
          }
        },
        {
          "id": "9918",
          "surah_order": "3297",
          "quran_order": "9447",
          "text": "وَالاَرْضِ",
          "surah_number": "3",
          "hizb_number": "8",
          "tomon_number": "3",
          "line_order": "8",
          "verse_order": "5",
          "is_last_word": "",
          "is_first_tomon": "",
          "verse": {
            "verse_number": "190",
            "next_verse": "191",
            "previous_verse": "189",
            "sajda": "",
            "is_last_verse": "",
            "is_number_linebreak": "",
            "wakf_end": "",
            "word_start": "9443",
            "word_stop": "9465"
          }
        },
        {
          "id": "9922",
          "surah_order": "3298",
          "quran_order": "9448",
          "text": "وَاخْتِچَـفِ",
          "surah_number": "3",
          "hizb_number": "8",
          "tomon_number": "3",
          "line_order": "9",
          "verse_order": "6",
          "is_last_word": "",
          "is_first_tomon": "",
          "verse": {
            "verse_number": "190",
            "next_verse": "191",
            "previous_verse": "189",
            "sajda": "",
            "is_last_verse": "",
            "is_number_linebreak": "",
            "wakf_end": "",
            "word_start": "9443",
            "word_stop": "9465"
          }
        }
      ]
    },
    {
      "line_id": 3,
      "line_number": 4,
      "is_surah_title": "",
      "surah_title": "ءَالِ عِمْرَانَ",
      "surah_title_ar": "آل عمران",
      "surah_title_lt": "Al-Imraan",
      "starts_with_verse_number": "",
      "words": [
        {
          "id": "9927",
          "surah_order": "3299",
          "quran_order": "9449",
          "text": "۱لـيْـلِ",
          "surah_number": "3",
          "hizb_number": "8",
          "tomon_number": "3",
          "line_order": "1",
          "verse_order": "7",
          "is_last_word": "",
          "is_first_tomon": "",
          "verse": {
            "verse_number": "190",
            "next_verse": "191",
            "previous_verse": "189",
            "sajda": "",
            "is_last_verse": "",
            "is_number_linebreak": "",
            "wakf_end": "",
            "word_start": "9443",
            "word_stop": "9465"
          }
        },
        {
          "id": "9929",
          "surah_order": "3300",
          "quran_order": "9450",
          "text": "وَالـنَّـهۭارۣ",
          "surah_number": "3",
          "hizb_number": "8",
          "tomon_number": "3",
          "line_order": "2",
          "verse_order": "8",
          "is_last_word": "",
          "is_first_tomon": "",
          "verse": {
            "verse_number": "190",
            "next_verse": "191",
            "previous_verse": "189",
            "sajda": "",
            "is_last_verse": "",
            "is_number_linebreak": "",
            "wakf_end": "",
            "word_start": "9443",
            "word_stop": "9465"
          }
        },
        {
          "id": "9932",
          "surah_order": "3301",
          "quran_order": "9451",
          "text": "ءَلاَيَــٰــتٍ",
          "surah_number": "3",
          "hizb_number": "8",
          "tomon_number": "3",
          "line_order": "3",
          "verse_order": "9",
          "is_last_word": "",
          "is_first_tomon": "",
          "verse": {
            "verse_number": "190",
            "next_verse": "191",
            "previous_verse": "189",
            "sajda": "",
            "is_last_verse": "",
            "is_number_linebreak": "",
            "wakf_end": "",
            "word_start": "9443",
            "word_stop": "9465"
          }
        },
        {
          "id": "9937",
          "surah_order": "3302",
          "quran_order": "9452",
          "text": "لُءِّوْلِى",
          "surah_number": "3",
          "hizb_number": "8",
          "tomon_number": "3",
          "line_order": "4",
          "verse_order": "10",
          "is_last_word": "",
          "is_first_tomon": "",
          "verse": {
            "verse_number": "190",
            "next_verse": "191",
            "previous_verse": "189",
            "sajda": "",
            "is_last_verse": "",
            "is_number_linebreak": "",
            "wakf_end": "",
            "word_start": "9443",
            "word_stop": "9465"
          }
        },
        {
          "id": "9945",
          "surah_order": "3303",
          "quran_order": "9453",
          "text": "۱لاَلْبَــٰــبِ",
          "surah_number": "3",
          "hizb_number": "8",
          "tomon_number": "3",
          "line_order": "5",
          "verse_order": "11",
          "is_last_word": "1",
          "is_first_tomon": "",
          "verse": {
            "verse_number": "190",
            "next_verse": "191",
            "previous_verse": "189",
            "sajda": "",
            "is_last_verse": "",
            "is_number_linebreak": "",
            "wakf_end": "",
            "word_start": "9443",
            "word_stop": "9465"
          }
        },
        {
          "id": "9952",
          "surah_order": "3304",
          "quran_order": "9454",
          "text": "۱لذِينَ",
          "surah_number": "3",
          "hizb_number": "8",
          "tomon_number": "3",
          "line_order": "6",
          "verse_order": "1",
          "is_last_word": "",
          "is_first_tomon": "",
          "verse": {
            "verse_number": "191",
            "next_verse": "192",
            "previous_verse": "190",
            "sajda": "",
            "is_last_verse": "",
            "is_number_linebreak": "",
            "wakf_end": "",
            "word_start": "9443",
            "word_stop": "9474"
          }
        },
        {
          "id": "9959",
          "surah_order": "3305",
          "quran_order": "9455",
          "text": "يَـذْكُـرُونَ",
          "surah_number": "3",
          "hizb_number": "8",
          "tomon_number": "3",
          "line_order": "7",
          "verse_order": "2",
          "is_last_word": "",
          "is_first_tomon": "",
          "verse": {
            "verse_number": "191",
            "next_verse": "192",
            "previous_verse": "190",
            "sajda": "",
            "is_last_verse": "",
            "is_number_linebreak": "",
            "wakf_end": "",
            "word_start": "9443",
            "word_stop": "9474"
          }
        }
      ]
    },
    {
      "line_id": 4,
      "line_number": 5,
      "is_surah_title": "",
      "surah_title": "ءَالِ عِمْرَانَ",
      "surah_title_ar": "آل عمران",
      "surah_title_lt": "Al-Imraan",
      "starts_with_verse_number": "",
      "words": [
        {
          "id": "9965",
          "surah_order": "3306",
          "quran_order": "9456",
          "text": "۰للَّهَ",
          "surah_number": "3",
          "hizb_number": "8",
          "tomon_number": "3",
          "line_order": "1",
          "verse_order": "3",
          "is_last_word": "",
          "is_first_tomon": "",
          "verse": {
            "verse_number": "191",
            "next_verse": "192",
            "previous_verse": "190",
            "sajda": "",
            "is_last_verse": "",
            "is_number_linebreak": "",
            "wakf_end": "",
            "word_start": "9443",
            "word_stop": "9474"
          }
        },
        {
          "id": "9969",
          "surah_order": "3307",
          "quran_order": "9457",
          "text": "قِـيَـــٰمـاً",
          "surah_number": "3",
          "hizb_number": "8",
          "tomon_number": "3",
          "line_order": "2",
          "verse_order": "4",
          "is_last_word": "",
          "is_first_tomon": "",
          "verse": {
            "verse_number": "191",
            "next_verse": "192",
            "previous_verse": "190",
            "sajda": "",
            "is_last_verse": "",
            "is_number_linebreak": "",
            "wakf_end": "",
            "word_start": "9443",
            "word_stop": "9474"
          }
        },
        {
          "id": "9976",
          "surah_order": "3308",
          "quran_order": "9458",
          "text": "وَقُـعُـوداً",
          "surah_number": "3",
          "hizb_number": "8",
          "tomon_number": "3",
          "line_order": "3",
          "verse_order": "5",
          "is_last_word": "",
          "is_first_tomon": "",
          "verse": {
            "verse_number": "191",
            "next_verse": "192",
            "previous_verse": "190",
            "sajda": "",
            "is_last_verse": "",
            "is_number_linebreak": "",
            "wakf_end": "",
            "word_start": "9443",
            "word_stop": "9474"
          }
        },
        {
          "id": "9979",
          "surah_order": "3309",
          "quran_order": "9459",
          "text": "وَعَـلَـيٰ",
          "surah_number": "3",
          "hizb_number": "8",
          "tomon_number": "3",
          "line_order": "4",
          "verse_order": "6",
          "is_last_word": "",
          "is_first_tomon": "",
          "verse": {
            "verse_number": "191",
            "next_verse": "192",
            "previous_verse": "190",
            "sajda": "",
            "is_last_verse": "",
            "is_number_linebreak": "",
            "wakf_end": "",
            "word_start": "9443",
            "word_stop": "9474"
          }
        },
        {
          "id": "9981",
          "surah_order": "3310",
          "quran_order": "9460",
          "text": "جُـنُـوبِهِمْ",
          "surah_number": "3",
          "hizb_number": "8",
          "tomon_number": "3",
          "line_order": "5",
          "verse_order": "7",
          "is_last_word": "",
          "is_first_tomon": "",
          "verse": {
            "verse_number": "191",
            "next_verse": "192",
            "previous_verse": "190",
            "sajda": "",
            "is_last_verse": "",
            "is_number_linebreak": "",
            "wakf_end": "",
            "word_start": "9443",
            "word_stop": "9474"
          }
        },
        {
          "id": "9983",
          "surah_order": "3311",
          "quran_order": "9461",
          "text": "وَيَـتَفَكَّـرُونَ",
          "surah_number": "3",
          "hizb_number": "8",
          "tomon_number": "3",
          "line_order": "6",
          "verse_order": "8",
          "is_last_word": "",
          "is_first_tomon": "",
          "verse": {
            "verse_number": "191",
            "next_verse": "192",
            "previous_verse": "190",
            "sajda": "",
            "is_last_verse": "",
            "is_number_linebreak": "",
            "wakf_end": "",
            "word_start": "9443",
            "word_stop": "9474"
          }
        },
        {
          "id": "9984",
          "surah_order": "3312",
          "quran_order": "9462",
          "text": "فِى",
          "surah_number": "3",
          "hizb_number": "8",
          "tomon_number": "3",
          "line_order": "7",
          "verse_order": "9",
          "is_last_word": "",
          "is_first_tomon": "",
          "verse": {
            "verse_number": "191",
            "next_verse": "192",
            "previous_verse": "190",
            "sajda": "",
            "is_last_verse": "",
            "is_number_linebreak": "",
            "wakf_end": "",
            "word_start": "9443",
            "word_stop": "9474"
          }
        },
        {
          "id": "9985",
          "surah_order": "3313",
          "quran_order": "9463",
          "text": "خَـلْـقِ",
          "surah_number": "3",
          "hizb_number": "8",
          "tomon_number": "3",
          "line_order": "8",
          "verse_order": "10",
          "is_last_word": "",
          "is_first_tomon": "",
          "verse": {
            "verse_number": "191",
            "next_verse": "192",
            "previous_verse": "190",
            "sajda": "",
            "is_last_verse": "",
            "is_number_linebreak": "",
            "wakf_end": "",
            "word_start": "9443",
            "word_stop": "9474"
          }
        }
      ]
    },
    {
      "line_id": 5,
      "line_number": 6,
      "is_surah_title": "",
      "surah_title": "ءَالِ عِمْرَانَ",
      "surah_title_ar": "آل عمران",
      "surah_title_lt": "Al-Imraan",
      "starts_with_verse_number": "",
      "words": [
        {
          "id": "9988",
          "surah_order": "3314",
          "quran_order": "9464",
          "text": "۱لسَّـمَــٰـوَ؛تتتِ",
          "surah_number": "3",
          "hizb_number": "8",
          "tomon_number": "3",
          "line_order": "1",
          "verse_order": "11",
          "is_last_word": "",
          "is_first_tomon": "",
          "verse": {
            "verse_number": "191",
            "next_verse": "192",
            "previous_verse": "190",
            "sajda": "",
            "is_last_verse": "",
            "is_number_linebreak": "",
            "wakf_end": "",
            "word_start": "9443",
            "word_stop": "9474"
          }
        },
        {
          "id": "9992",
          "surah_order": "3315",
          "quran_order": "9465",
          "text": "وَالاَرْضِؐ",
          "surah_number": "3",
          "hizb_number": "8",
          "tomon_number": "3",
          "line_order": "2",
          "verse_order": "12",
          "is_last_word": "",
          "is_first_tomon": "",
          "verse": {
            "verse_number": "191",
            "next_verse": "192",
            "previous_verse": "190",
            "sajda": "",
            "is_last_verse": "",
            "is_number_linebreak": "",
            "wakf_end": "",
            "word_start": "9443",
            "word_stop": "9474"
          }
        },
        {
          "id": "9996",
          "surah_order": "3316",
          "quran_order": "9466",
          "text": "رَبَّــنَــا",
          "surah_number": "3",
          "hizb_number": "8",
          "tomon_number": "3",
          "line_order": "3",
          "verse_order": "13",
          "is_last_word": "",
          "is_first_tomon": "",
          "verse": {
            "verse_number": "191",
            "next_verse": "192",
            "previous_verse": "190",
            "sajda": "",
            "is_last_verse": "",
            "is_number_linebreak": "",
            "wakf_end": "",
            "word_start": "9443",
            "word_stop": "9474"
          }
        },
        {
          "id": "10000",
          "surah_order": "3317",
          "quran_order": "9467",
          "text": "مَـا",
          "surah_number": "3",
          "hizb_number": "8",
          "tomon_number": "3",
          "line_order": "4",
          "verse_order": "14",
          "is_last_word": "",
          "is_first_tomon": "",
          "verse": {
            "verse_number": "191",
            "next_verse": "192",
            "previous_verse": "190",
            "sajda": "",
            "is_last_verse": "",
            "is_number_linebreak": "",
            "wakf_end": "",
            "word_start": "9443",
            "word_stop": "9474"
          }
        },
        {
          "id": "10009",
          "surah_order": "3318",
          "quran_order": "9468",
          "text": "خَلَقْــتَ",
          "surah_number": "3",
          "hizb_number": "8",
          "tomon_number": "3",
          "line_order": "5",
          "verse_order": "15",
          "is_last_word": "",
          "is_first_tomon": "",
          "verse": {
            "verse_number": "191",
            "next_verse": "192",
            "previous_verse": "190",
            "sajda": "",
            "is_last_verse": "",
            "is_number_linebreak": "",
            "wakf_end": "",
            "word_start": "9443",
            "word_stop": "9474"
          }
        },
        {
          "id": "10011",
          "surah_order": "3319",
          "quran_order": "9469",
          "text": "هَــٰذَا",
          "surah_number": "3",
          "hizb_number": "8",
          "tomon_number": "3",
          "line_order": "6",
          "verse_order": "16",
          "is_last_word": "",
          "is_first_tomon": "",
          "verse": {
            "verse_number": "191",
            "next_verse": "192",
            "previous_verse": "190",
            "sajda": "",
            "is_last_verse": "",
            "is_number_linebreak": "",
            "wakf_end": "",
            "word_start": "9443",
            "word_stop": "9474"
          }
        },
        {
          "id": "10016",
          "surah_order": "3320",
          "quran_order": "9470",
          "text": "بَــٰطِلًا",
          "surah_number": "3",
          "hizb_number": "8",
          "tomon_number": "3",
          "line_order": "7",
          "verse_order": "17",
          "is_last_word": "",
          "is_first_tomon": "",
          "verse": {
            "verse_number": "191",
            "next_verse": "192",
            "previous_verse": "190",
            "sajda": "",
            "is_last_verse": "",
            "is_number_linebreak": "",
            "wakf_end": "",
            "word_start": "9443",
            "word_stop": "9474"
          }
        },
        {
          "id": "10020",
          "surah_order": "3321",
          "quran_order": "9471",
          "text": "سُبْحَــٰنَكَؐ",
          "surah_number": "3",
          "hizb_number": "8",
          "tomon_number": "3",
          "line_order": "8",
          "verse_order": "18",
          "is_last_word": "",
          "is_first_tomon": "",
          "verse": {
            "verse_number": "191",
            "next_verse": "192",
            "previous_verse": "190",
            "sajda": "",
            "is_last_verse": "",
            "is_number_linebreak": "",
            "wakf_end": "",
            "word_start": "9443",
            "word_stop": "9474"
          }
        }
      ]
    },
    {
      "line_id": 6,
      "line_number": 7,
      "is_surah_title": "",
      "surah_title": "ءَالِ عِمْرَانَ",
      "surah_title_ar": "آل عمران",
      "surah_title_lt": "Al-Imraan",
      "starts_with_verse_number": "",
      "words": [
        {
          "id": "10025",
          "surah_order": "3322",
          "quran_order": "9472",
          "text": "فَقِنَا",
          "surah_number": "3",
          "hizb_number": "8",
          "tomon_number": "3",
          "line_order": "1",
          "verse_order": "19",
          "is_last_word": "",
          "is_first_tomon": "",
          "verse": {
            "verse_number": "191",
            "next_verse": "192",
            "previous_verse": "190",
            "sajda": "",
            "is_last_verse": "",
            "is_number_linebreak": "",
            "wakf_end": "",
            "word_start": "9443",
            "word_stop": "9474"
          }
        },
        {
          "id": "10028",
          "surah_order": "3323",
          "quran_order": "9473",
          "text": "عَذَابببَ",
          "surah_number": "3",
          "hizb_number": "8",
          "tomon_number": "3",
          "line_order": "2",
          "verse_order": "20",
          "is_last_word": "",
          "is_first_tomon": "",
          "verse": {
            "verse_number": "191",
            "next_verse": "192",
            "previous_verse": "190",
            "sajda": "",
            "is_last_verse": "",
            "is_number_linebreak": "",
            "wakf_end": "",
            "word_start": "9443",
            "word_stop": "9474"
          }
        },
        {
          "id": "10035",
          "surah_order": "3324",
          "quran_order": "9474",
          "text": "۰لنّۭارۣؐ",
          "surah_number": "3",
          "hizb_number": "8",
          "tomon_number": "3",
          "line_order": "3",
          "verse_order": "21",
          "is_last_word": "1",
          "is_first_tomon": "",
          "verse": {
            "verse_number": "191",
            "next_verse": "192",
            "previous_verse": "190",
            "sajda": "",
            "is_last_verse": "",
            "is_number_linebreak": "",
            "wakf_end": "",
            "word_start": "9443",
            "word_stop": "9474"
          }
        },
        {
          "id": "10042",
          "surah_order": "3325",
          "quran_order": "9475",
          "text": "رَبَّنَآ",
          "surah_number": "3",
          "hizb_number": "8",
          "tomon_number": "3",
          "line_order": "4",
          "verse_order": "1",
          "is_last_word": "",
          "is_first_tomon": "",
          "verse": {
            "verse_number": "192",
            "next_verse": "193",
            "previous_verse": "191",
            "sajda": "",
            "is_last_verse": "",
            "is_number_linebreak": "",
            "wakf_end": "",
            "word_start": "9475",
            "word_stop": "9485"
          }
        },
        {
          "id": "10047",
          "surah_order": "3326",
          "quran_order": "9476",
          "text": "إِنَّكَ",
          "surah_number": "3",
          "hizb_number": "8",
          "tomon_number": "3",
          "line_order": "5",
          "verse_order": "2",
          "is_last_word": "",
          "is_first_tomon": "",
          "verse": {
            "verse_number": "192",
            "next_verse": "193",
            "previous_verse": "191",
            "sajda": "",
            "is_last_verse": "",
            "is_number_linebreak": "",
            "wakf_end": "",
            "word_start": "9475",
            "word_stop": "9485"
          }
        },
        {
          "id": "10053",
          "surah_order": "3327",
          "quran_order": "9477",
          "text": "مَــن",
          "surah_number": "3",
          "hizb_number": "8",
          "tomon_number": "3",
          "line_order": "6",
          "verse_order": "3",
          "is_last_word": "",
          "is_first_tomon": "",
          "verse": {
            "verse_number": "192",
            "next_verse": "193",
            "previous_verse": "191",
            "sajda": "",
            "is_last_verse": "",
            "is_number_linebreak": "",
            "wakf_end": "",
            "word_start": "9475",
            "word_stop": "9485"
          }
        },
        {
          "id": "10057",
          "surah_order": "3328",
          "quran_order": "9478",
          "text": "تُدْخِلِ",
          "surah_number": "3",
          "hizb_number": "8",
          "tomon_number": "3",
          "line_order": "7",
          "verse_order": "4",
          "is_last_word": "",
          "is_first_tomon": "",
          "verse": {
            "verse_number": "192",
            "next_verse": "193",
            "previous_verse": "191",
            "sajda": "",
            "is_last_verse": "",
            "is_number_linebreak": "",
            "wakf_end": "",
            "word_start": "9475",
            "word_stop": "9485"
          }
        },
        {
          "id": "10064",
          "surah_order": "3329",
          "quran_order": "9479",
          "text": "۱لنَّارَ",
          "surah_number": "3",
          "hizb_number": "8",
          "tomon_number": "3",
          "line_order": "8",
          "verse_order": "5",
          "is_last_word": "",
          "is_first_tomon": "",
          "verse": {
            "verse_number": "192",
            "next_verse": "193",
            "previous_verse": "191",
            "sajda": "",
            "is_last_verse": "",
            "is_number_linebreak": "",
            "wakf_end": "",
            "word_start": "9475",
            "word_stop": "9485"
          }
        },
        {
          "id": "10072",
          "surah_order": "3330",
          "quran_order": "9480",
          "text": "فَقَدَ",
          "surah_number": "3",
          "hizb_number": "8",
          "tomon_number": "3",
          "line_order": "9",
          "verse_order": "6",
          "is_last_word": "",
          "is_first_tomon": "",
          "verse": {
            "verse_number": "192",
            "next_verse": "193",
            "previous_verse": "191",
            "sajda": "",
            "is_last_verse": "",
            "is_number_linebreak": "",
            "wakf_end": "",
            "word_start": "9475",
            "word_stop": "9485"
          }
        },
        {
          "id": "10075",
          "surah_order": "3331",
          "quran_order": "9481",
          "text": "اَخْزَيْتَهُؐ,",
          "surah_number": "3",
          "hizb_number": "8",
          "tomon_number": "3",
          "line_order": "10",
          "verse_order": "7",
          "is_last_word": "",
          "is_first_tomon": "",
          "verse": {
            "verse_number": "192",
            "next_verse": "193",
            "previous_verse": "191",
            "sajda": "",
            "is_last_verse": "",
            "is_number_linebreak": "",
            "wakf_end": "",
            "word_start": "9475",
            "word_stop": "9485"
          }
        }
      ]
    },
    {
      "line_id": 7,
      "line_number": 8,
      "is_surah_title": "",
      "surah_title": "ءَالِ عِمْرَانَ",
      "surah_title_ar": "آل عمران",
      "surah_title_lt": "Al-Imraan",
      "starts_with_verse_number": "",
      "words": [
        {
          "id": "10084",
          "surah_order": "3332",
          "quran_order": "9482",
          "text": "وَمَا",
          "surah_number": "3",
          "hizb_number": "8",
          "tomon_number": "3",
          "line_order": "1",
          "verse_order": "8",
          "is_last_word": "",
          "is_first_tomon": "",
          "verse": {
            "verse_number": "192",
            "next_verse": "193",
            "previous_verse": "191",
            "sajda": "",
            "is_last_verse": "",
            "is_number_linebreak": "",
            "wakf_end": "",
            "word_start": "9475",
            "word_stop": "9485"
          }
        },
        {
          "id": "10092",
          "surah_order": "3333",
          "quran_order": "9483",
          "text": "لِلظَّــٰلِمِيــنَ",
          "surah_number": "3",
          "hizb_number": "8",
          "tomon_number": "3",
          "line_order": "2",
          "verse_order": "9",
          "is_last_word": "",
          "is_first_tomon": "",
          "verse": {
            "verse_number": "192",
            "next_verse": "193",
            "previous_verse": "191",
            "sajda": "",
            "is_last_verse": "",
            "is_number_linebreak": "",
            "wakf_end": "",
            "word_start": "9475",
            "word_stop": "9485"
          }
        },
        {
          "id": "10096",
          "surah_order": "3334",
          "quran_order": "9484",
          "text": "مِنَ",
          "surah_number": "3",
          "hizb_number": "8",
          "tomon_number": "3",
          "line_order": "3",
          "verse_order": "10",
          "is_last_word": "",
          "is_first_tomon": "",
          "verse": {
            "verse_number": "192",
            "next_verse": "193",
            "previous_verse": "191",
            "sajda": "",
            "is_last_verse": "",
            "is_number_linebreak": "",
            "wakf_end": "",
            "word_start": "9475",
            "word_stop": "9485"
          }
        },
        {
          "id": "10101",
          "surah_order": "3335",
          "quran_order": "9485",
          "text": "اَنصۭارٍؐ",
          "surah_number": "3",
          "hizb_number": "8",
          "tomon_number": "3",
          "line_order": "4",
          "verse_order": "11",
          "is_last_word": "1",
          "is_first_tomon": "",
          "verse": {
            "verse_number": "192",
            "next_verse": "193",
            "previous_verse": "191",
            "sajda": "",
            "is_last_verse": "",
            "is_number_linebreak": "",
            "wakf_end": "",
            "word_start": "9475",
            "word_stop": "9485"
          }
        },
        {
          "id": "10109",
          "surah_order": "3336",
          "quran_order": "9486",
          "text": "رَّبَّنَآ",
          "surah_number": "3",
          "hizb_number": "8",
          "tomon_number": "3",
          "line_order": "5",
          "verse_order": "1",
          "is_last_word": "",
          "is_first_tomon": "",
          "verse": {
            "verse_number": "193",
            "next_verse": "194",
            "previous_verse": "192",
            "sajda": "",
            "is_last_verse": "",
            "is_number_linebreak": "",
            "wakf_end": "",
            "word_start": "9486",
            "word_stop": "9505"
          }
        },
        {
          "id": "10117",
          "surah_order": "3337",
          "quran_order": "9487",
          "text": "إِنَّنَا",
          "surah_number": "3",
          "hizb_number": "8",
          "tomon_number": "3",
          "line_order": "6",
          "verse_order": "2",
          "is_last_word": "",
          "is_first_tomon": "",
          "verse": {
            "verse_number": "193",
            "next_verse": "194",
            "previous_verse": "192",
            "sajda": "",
            "is_last_verse": "",
            "is_number_linebreak": "",
            "wakf_end": "",
            "word_start": "9486",
            "word_stop": "9505"
          }
        },
        {
          "id": "10125",
          "surah_order": "3338",
          "quran_order": "9488",
          "text": "سَمِعْنَا",
          "surah_number": "3",
          "hizb_number": "8",
          "tomon_number": "3",
          "line_order": "7",
          "verse_order": "3",
          "is_last_word": "",
          "is_first_tomon": "",
          "verse": {
            "verse_number": "193",
            "next_verse": "194",
            "previous_verse": "192",
            "sajda": "",
            "is_last_verse": "",
            "is_number_linebreak": "",
            "wakf_end": "",
            "word_start": "9486",
            "word_stop": "9505"
          }
        },
        {
          "id": "10127",
          "surah_order": "3339",
          "quran_order": "9489",
          "text": "مُنَادِياً",
          "surah_number": "3",
          "hizb_number": "8",
          "tomon_number": "3",
          "line_order": "8",
          "verse_order": "4",
          "is_last_word": "",
          "is_first_tomon": "",
          "verse": {
            "verse_number": "193",
            "next_verse": "194",
            "previous_verse": "192",
            "sajda": "",
            "is_last_verse": "",
            "is_number_linebreak": "",
            "wakf_end": "",
            "word_start": "9486",
            "word_stop": "9505"
          }
        },
        {
          "id": "10134",
          "surah_order": "3340",
          "quran_order": "9490",
          "text": "يُنَادِى",
          "surah_number": "3",
          "hizb_number": "8",
          "tomon_number": "3",
          "line_order": "9",
          "verse_order": "5",
          "is_last_word": "",
          "is_first_tomon": "",
          "verse": {
            "verse_number": "193",
            "next_verse": "194",
            "previous_verse": "192",
            "sajda": "",
            "is_last_verse": "",
            "is_number_linebreak": "",
            "wakf_end": "",
            "word_start": "9486",
            "word_stop": "9505"
          }
        }
      ]
    },
    {
      "line_id": 8,
      "line_number": 9,
      "is_surah_title": "",
      "surah_title": "ءَالِ عِمْرَانَ",
      "surah_title_ar": "آل عمران",
      "surah_title_lt": "Al-Imraan",
      "starts_with_verse_number": "",
      "words": [
        {
          "id": "10139",
          "surah_order": "3341",
          "quran_order": "9491",
          "text": "لِـلِايـمَـٰنِ",
          "surah_number": "3",
          "hizb_number": "8",
          "tomon_number": "3",
          "line_order": "1",
          "verse_order": "6",
          "is_last_word": "",
          "is_first_tomon": "",
          "verse": {
            "verse_number": "193",
            "next_verse": "194",
            "previous_verse": "192",
            "sajda": "",
            "is_last_verse": "",
            "is_number_linebreak": "",
            "wakf_end": "",
            "word_start": "9486",
            "word_stop": "9505"
          }
        },
        {
          "id": "10141",
          "surah_order": "3342",
          "quran_order": "9492",
          "text": "أَنَ",
          "surah_number": "3",
          "hizb_number": "8",
          "tomon_number": "3",
          "line_order": "2",
          "verse_order": "7",
          "is_last_word": "",
          "is_first_tomon": "",
          "verse": {
            "verse_number": "193",
            "next_verse": "194",
            "previous_verse": "192",
            "sajda": "",
            "is_last_verse": "",
            "is_number_linebreak": "",
            "wakf_end": "",
            "word_start": "9486",
            "word_stop": "9505"
          }
        },
        {
          "id": "10142",
          "surah_order": "3343",
          "quran_order": "9493",
          "text": "—امِـنُـواْ",
          "surah_number": "3",
          "hizb_number": "8",
          "tomon_number": "3",
          "line_order": "3",
          "verse_order": "8",
          "is_last_word": "",
          "is_first_tomon": "",
          "verse": {
            "verse_number": "193",
            "next_verse": "194",
            "previous_verse": "192",
            "sajda": "",
            "is_last_verse": "",
            "is_number_linebreak": "",
            "wakf_end": "",
            "word_start": "9486",
            "word_stop": "9505"
          }
        },
        {
          "id": "10143",
          "surah_order": "3344",
          "quran_order": "9494",
          "text": "بِـرَبِّـكُـمْ",
          "surah_number": "3",
          "hizb_number": "8",
          "tomon_number": "3",
          "line_order": "4",
          "verse_order": "9",
          "is_last_word": "",
          "is_first_tomon": "",
          "verse": {
            "verse_number": "193",
            "next_verse": "194",
            "previous_verse": "192",
            "sajda": "",
            "is_last_verse": "",
            "is_number_linebreak": "",
            "wakf_end": "",
            "word_start": "9486",
            "word_stop": "9505"
          }
        },
        {
          "id": "10144",
          "surah_order": "3345",
          "quran_order": "9495",
          "text": "فَــَٔامَنَّاؐ",
          "surah_number": "3",
          "hizb_number": "8",
          "tomon_number": "3",
          "line_order": "5",
          "verse_order": "10",
          "is_last_word": "",
          "is_first_tomon": "",
          "verse": {
            "verse_number": "193",
            "next_verse": "194",
            "previous_verse": "192",
            "sajda": "",
            "is_last_verse": "",
            "is_number_linebreak": "",
            "wakf_end": "",
            "word_start": "9486",
            "word_stop": "9505"
          }
        },
        {
          "id": "10146",
          "surah_order": "3346",
          "quran_order": "9496",
          "text": "رَبَّـنَـا",
          "surah_number": "3",
          "hizb_number": "8",
          "tomon_number": "3",
          "line_order": "6",
          "verse_order": "11",
          "is_last_word": "",
          "is_first_tomon": "",
          "verse": {
            "verse_number": "193",
            "next_verse": "194",
            "previous_verse": "192",
            "sajda": "",
            "is_last_verse": "",
            "is_number_linebreak": "",
            "wakf_end": "",
            "word_start": "9486",
            "word_stop": "9505"
          }
        },
        {
          "id": "10148",
          "surah_order": "3347",
          "quran_order": "9497",
          "text": "فَاغْفِرْ",
          "surah_number": "3",
          "hizb_number": "8",
          "tomon_number": "3",
          "line_order": "7",
          "verse_order": "12",
          "is_last_word": "",
          "is_first_tomon": "",
          "verse": {
            "verse_number": "193",
            "next_verse": "194",
            "previous_verse": "192",
            "sajda": "",
            "is_last_verse": "",
            "is_number_linebreak": "",
            "wakf_end": "",
            "word_start": "9486",
            "word_stop": "9505"
          }
        },
        {
          "id": "10155",
          "surah_order": "3348",
          "quran_order": "9498",
          "text": "لَنَا",
          "surah_number": "3",
          "hizb_number": "8",
          "tomon_number": "3",
          "line_order": "8",
          "verse_order": "13",
          "is_last_word": "",
          "is_first_tomon": "",
          "verse": {
            "verse_number": "193",
            "next_verse": "194",
            "previous_verse": "192",
            "sajda": "",
            "is_last_verse": "",
            "is_number_linebreak": "",
            "wakf_end": "",
            "word_start": "9486",
            "word_stop": "9505"
          }
        },
        {
          "id": "10157",
          "surah_order": "3349",
          "quran_order": "9499",
          "text": "ذُنُوبَنَــا",
          "surah_number": "3",
          "hizb_number": "8",
          "tomon_number": "3",
          "line_order": "9",
          "verse_order": "14",
          "is_last_word": "",
          "is_first_tomon": "",
          "verse": {
            "verse_number": "193",
            "next_verse": "194",
            "previous_verse": "192",
            "sajda": "",
            "is_last_verse": "",
            "is_number_linebreak": "",
            "wakf_end": "",
            "word_start": "9486",
            "word_stop": "9505"
          }
        }
      ]
    },
    {
      "line_id": 9,
      "line_number": 10,
      "is_surah_title": "",
      "surah_title": "ءَالِ عِمْرَانَ",
      "surah_title_ar": "آل عمران",
      "surah_title_lt": "Al-Imraan",
      "starts_with_verse_number": "",
      "words": [
        {
          "id": "10158",
          "surah_order": "3350",
          "quran_order": "9500",
          "text": "وَكَـفِّـرْ",
          "surah_number": "3",
          "hizb_number": "8",
          "tomon_number": "3",
          "line_order": "1",
          "verse_order": "15",
          "is_last_word": "",
          "is_first_tomon": "",
          "verse": {
            "verse_number": "193",
            "next_verse": "194",
            "previous_verse": "192",
            "sajda": "",
            "is_last_verse": "",
            "is_number_linebreak": "",
            "wakf_end": "",
            "word_start": "9486",
            "word_stop": "9505"
          }
        },
        {
          "id": "10159",
          "surah_order": "3351",
          "quran_order": "9501",
          "text": "عَـنَّـا",
          "surah_number": "3",
          "hizb_number": "8",
          "tomon_number": "3",
          "line_order": "2",
          "verse_order": "16",
          "is_last_word": "",
          "is_first_tomon": "",
          "verse": {
            "verse_number": "193",
            "next_verse": "194",
            "previous_verse": "192",
            "sajda": "",
            "is_last_verse": "",
            "is_number_linebreak": "",
            "wakf_end": "",
            "word_start": "9486",
            "word_stop": "9505"
          }
        },
        {
          "id": "10160",
          "surah_order": "3352",
          "quran_order": "9502",
          "text": "سَـيِّــَٔاتِـنَـا",
          "surah_number": "3",
          "hizb_number": "8",
          "tomon_number": "3",
          "line_order": "3",
          "verse_order": "17",
          "is_last_word": "",
          "is_first_tomon": "",
          "verse": {
            "verse_number": "193",
            "next_verse": "194",
            "previous_verse": "192",
            "sajda": "",
            "is_last_verse": "",
            "is_number_linebreak": "",
            "wakf_end": "",
            "word_start": "9486",
            "word_stop": "9505"
          }
        },
        {
          "id": "10161",
          "surah_order": "3353",
          "quran_order": "9503",
          "text": "وَتَـوَفَّـنَـا",
          "surah_number": "3",
          "hizb_number": "8",
          "tomon_number": "3",
          "line_order": "4",
          "verse_order": "18",
          "is_last_word": "",
          "is_first_tomon": "",
          "verse": {
            "verse_number": "193",
            "next_verse": "194",
            "previous_verse": "192",
            "sajda": "",
            "is_last_verse": "",
            "is_number_linebreak": "",
            "wakf_end": "",
            "word_start": "9486",
            "word_stop": "9505"
          }
        },
        {
          "id": "10162",
          "surah_order": "3354",
          "quran_order": "9504",
          "text": "مَـعَ",
          "surah_number": "3",
          "hizb_number": "8",
          "tomon_number": "3",
          "line_order": "5",
          "verse_order": "19",
          "is_last_word": "",
          "is_first_tomon": "",
          "verse": {
            "verse_number": "193",
            "next_verse": "194",
            "previous_verse": "192",
            "sajda": "",
            "is_last_verse": "",
            "is_number_linebreak": "",
            "wakf_end": "",
            "word_start": "9486",
            "word_stop": "9505"
          }
        },
        {
          "id": "10163",
          "surah_order": "3355",
          "quran_order": "9505",
          "text": "۰لاَبْرۭارۣؐ",
          "surah_number": "3",
          "hizb_number": "8",
          "tomon_number": "3",
          "line_order": "6",
          "verse_order": "20",
          "is_last_word": "1",
          "is_first_tomon": "",
          "verse": {
            "verse_number": "193",
            "next_verse": "194",
            "previous_verse": "192",
            "sajda": "",
            "is_last_verse": "",
            "is_number_linebreak": "",
            "wakf_end": "",
            "word_start": "9486",
            "word_stop": "9505"
          }
        },
        {
          "id": "10185",
          "surah_order": "3356",
          "quran_order": "9506",
          "text": "رَبَّنَا",
          "surah_number": "3",
          "hizb_number": "8",
          "tomon_number": "3",
          "line_order": "7",
          "verse_order": "1",
          "is_last_word": "",
          "is_first_tomon": "",
          "verse": {
            "verse_number": "194",
            "next_verse": "195",
            "previous_verse": "193",
            "sajda": "",
            "is_last_verse": "",
            "is_number_linebreak": "",
            "wakf_end": "",
            "word_start": "9506",
            "word_stop": "9519"
          }
        },
        {
          "id": "10186",
          "surah_order": "3357",
          "quran_order": "9507",
          "text": "وَءَاتِنَــا",
          "surah_number": "3",
          "hizb_number": "8",
          "tomon_number": "3",
          "line_order": "8",
          "verse_order": "2",
          "is_last_word": "",
          "is_first_tomon": "",
          "verse": {
            "verse_number": "194",
            "next_verse": "195",
            "previous_verse": "193",
            "sajda": "",
            "is_last_verse": "",
            "is_number_linebreak": "",
            "wakf_end": "",
            "word_start": "9506",
            "word_stop": "9519"
          }
        }
      ]
    },
    {
      "line_id": 10,
      "line_number": 11,
      "is_surah_title": "",
      "surah_title": "ءَالِ عِمْرَانَ",
      "surah_title_ar": "آل عمران",
      "surah_title_lt": "Al-Imraan",
      "starts_with_verse_number": "",
      "words": [
        {
          "id": "10188",
          "surah_order": "3358",
          "quran_order": "9508",
          "text": "مَـا",
          "surah_number": "3",
          "hizb_number": "8",
          "tomon_number": "3",
          "line_order": "1",
          "verse_order": "3",
          "is_last_word": "",
          "is_first_tomon": "",
          "verse": {
            "verse_number": "194",
            "next_verse": "195",
            "previous_verse": "193",
            "sajda": "",
            "is_last_verse": "",
            "is_number_linebreak": "",
            "wakf_end": "",
            "word_start": "9506",
            "word_stop": "9519"
          }
        },
        {
          "id": "10191",
          "surah_order": "3359",
          "quran_order": "9509",
          "text": "وَعَدتَّنَا",
          "surah_number": "3",
          "hizb_number": "8",
          "tomon_number": "3",
          "line_order": "2",
          "verse_order": "4",
          "is_last_word": "",
          "is_first_tomon": "",
          "verse": {
            "verse_number": "194",
            "next_verse": "195",
            "previous_verse": "193",
            "sajda": "",
            "is_last_verse": "",
            "is_number_linebreak": "",
            "wakf_end": "",
            "word_start": "9506",
            "word_stop": "9519"
          }
        },
        {
          "id": "10192",
          "surah_order": "3360",
          "quran_order": "9510",
          "text": "عَلَيٰ",
          "surah_number": "3",
          "hizb_number": "8",
          "tomon_number": "3",
          "line_order": "3",
          "verse_order": "5",
          "is_last_word": "",
          "is_first_tomon": "",
          "verse": {
            "verse_number": "194",
            "next_verse": "195",
            "previous_verse": "193",
            "sajda": "",
            "is_last_verse": "",
            "is_number_linebreak": "",
            "wakf_end": "",
            "word_start": "9506",
            "word_stop": "9519"
          }
        },
        {
          "id": "10193",
          "surah_order": "3361",
          "quran_order": "9511",
          "text": "رُسُلِكَ",
          "surah_number": "3",
          "hizb_number": "8",
          "tomon_number": "3",
          "line_order": "4",
          "verse_order": "6",
          "is_last_word": "",
          "is_first_tomon": "",
          "verse": {
            "verse_number": "194",
            "next_verse": "195",
            "previous_verse": "193",
            "sajda": "",
            "is_last_verse": "",
            "is_number_linebreak": "",
            "wakf_end": "",
            "word_start": "9506",
            "word_stop": "9519"
          }
        },
        {
          "id": "10195",
          "surah_order": "3362",
          "quran_order": "9512",
          "text": "وَلاَ",
          "surah_number": "3",
          "hizb_number": "8",
          "tomon_number": "3",
          "line_order": "5",
          "verse_order": "7",
          "is_last_word": "",
          "is_first_tomon": "",
          "verse": {
            "verse_number": "194",
            "next_verse": "195",
            "previous_verse": "193",
            "sajda": "",
            "is_last_verse": "",
            "is_number_linebreak": "",
            "wakf_end": "",
            "word_start": "9506",
            "word_stop": "9519"
          }
        },
        {
          "id": "10198",
          "surah_order": "3363",
          "quran_order": "9513",
          "text": "تُخْزۣنَا",
          "surah_number": "3",
          "hizb_number": "8",
          "tomon_number": "3",
          "line_order": "6",
          "verse_order": "8",
          "is_last_word": "",
          "is_first_tomon": "",
          "verse": {
            "verse_number": "194",
            "next_verse": "195",
            "previous_verse": "193",
            "sajda": "",
            "is_last_verse": "",
            "is_number_linebreak": "",
            "wakf_end": "",
            "word_start": "9506",
            "word_stop": "9519"
          }
        },
        {
          "id": "10203",
          "surah_order": "3364",
          "quran_order": "9514",
          "text": "يَوْمَ",
          "surah_number": "3",
          "hizb_number": "8",
          "tomon_number": "3",
          "line_order": "7",
          "verse_order": "9",
          "is_last_word": "",
          "is_first_tomon": "",
          "verse": {
            "verse_number": "194",
            "next_verse": "195",
            "previous_verse": "193",
            "sajda": "",
            "is_last_verse": "",
            "is_number_linebreak": "",
            "wakf_end": "",
            "word_start": "9506",
            "word_stop": "9519"
          }
        },
        {
          "id": "10205",
          "surah_order": "3365",
          "quran_order": "9515",
          "text": "۰لْقِيَــٰمَةِؐ",
          "surah_number": "3",
          "hizb_number": "8",
          "tomon_number": "3",
          "line_order": "8",
          "verse_order": "10",
          "is_last_word": "",
          "is_first_tomon": "",
          "verse": {
            "verse_number": "194",
            "next_verse": "195",
            "previous_verse": "193",
            "sajda": "",
            "is_last_verse": "",
            "is_number_linebreak": "",
            "wakf_end": "",
            "word_start": "9506",
            "word_stop": "9519"
          }
        },
        {
          "id": "10206",
          "surah_order": "3366",
          "quran_order": "9516",
          "text": "إِنَّژَ",
          "surah_number": "3",
          "hizb_number": "8",
          "tomon_number": "3",
          "line_order": "9",
          "verse_order": "11",
          "is_last_word": "",
          "is_first_tomon": "",
          "verse": {
            "verse_number": "194",
            "next_verse": "195",
            "previous_verse": "193",
            "sajda": "",
            "is_last_verse": "",
            "is_number_linebreak": "",
            "wakf_end": "",
            "word_start": "9506",
            "word_stop": "9519"
          }
        },
        {
          "id": "10208",
          "surah_order": "3367",
          "quran_order": "9517",
          "text": "لاَ",
          "surah_number": "3",
          "hizb_number": "8",
          "tomon_number": "3",
          "line_order": "10",
          "verse_order": "12",
          "is_last_word": "",
          "is_first_tomon": "",
          "verse": {
            "verse_number": "194",
            "next_verse": "195",
            "previous_verse": "193",
            "sajda": "",
            "is_last_verse": "",
            "is_number_linebreak": "",
            "wakf_end": "",
            "word_start": "9506",
            "word_stop": "9519"
          }
        },
        {
          "id": "10210",
          "surah_order": "3368",
          "quran_order": "9518",
          "text": "تُخْلِـفُ",
          "surah_number": "3",
          "hizb_number": "8",
          "tomon_number": "3",
          "line_order": "11",
          "verse_order": "13",
          "is_last_word": "",
          "is_first_tomon": "",
          "verse": {
            "verse_number": "194",
            "next_verse": "195",
            "previous_verse": "193",
            "sajda": "",
            "is_last_verse": "",
            "is_number_linebreak": "",
            "wakf_end": "",
            "word_start": "9506",
            "word_stop": "9519"
          }
        }
      ]
    },
    {
      "line_id": 11,
      "line_number": 12,
      "is_surah_title": "",
      "surah_title": "ءَالِ عِمْرَانَ",
      "surah_title_ar": "آل عمران",
      "surah_title_lt": "Al-Imraan",
      "starts_with_verse_number": "",
      "words": [
        {
          "id": "10213",
          "surah_order": "3369",
          "quran_order": "9519",
          "text": "۴لْمِيعَادَؐ",
          "surah_number": "3",
          "hizb_number": "8",
          "tomon_number": "3",
          "line_order": "1",
          "verse_order": "14",
          "is_last_word": "1",
          "is_first_tomon": "",
          "verse": {
            "verse_number": "194",
            "next_verse": "195",
            "previous_verse": "193",
            "sajda": "",
            "is_last_verse": "",
            "is_number_linebreak": "",
            "wakf_end": "",
            "word_start": "9506",
            "word_stop": "9519"
          }
        },
        {
          "id": "10219",
          "surah_order": "3370",
          "quran_order": "9520",
          "text": "فَاسْـتَجَابببَ",
          "surah_number": "3",
          "hizb_number": "8",
          "tomon_number": "3",
          "line_order": "2",
          "verse_order": "1",
          "is_last_word": "",
          "is_first_tomon": "",
          "verse": {
            "verse_number": "195",
            "next_verse": "196",
            "previous_verse": "194",
            "sajda": "",
            "is_last_verse": "",
            "is_number_linebreak": "",
            "wakf_end": "",
            "word_start": "9520",
            "word_stop": "9562"
          }
        },
        {
          "id": "10220",
          "surah_order": "3371",
          "quran_order": "9521",
          "text": "لَهُمْ",
          "surah_number": "3",
          "hizb_number": "8",
          "tomon_number": "3",
          "line_order": "3",
          "verse_order": "2",
          "is_last_word": "",
          "is_first_tomon": "",
          "verse": {
            "verse_number": "195",
            "next_verse": "196",
            "previous_verse": "194",
            "sajda": "",
            "is_last_verse": "",
            "is_number_linebreak": "",
            "wakf_end": "",
            "word_start": "9520",
            "word_stop": "9562"
          }
        },
        {
          "id": "10223",
          "surah_order": "3372",
          "quran_order": "9522",
          "text": "رَبُّهُمُ;",
          "surah_number": "3",
          "hizb_number": "8",
          "tomon_number": "3",
          "line_order": "4",
          "verse_order": "3",
          "is_last_word": "",
          "is_first_tomon": "",
          "verse": {
            "verse_number": "195",
            "next_verse": "196",
            "previous_verse": "194",
            "sajda": "",
            "is_last_verse": "",
            "is_number_linebreak": "",
            "wakf_end": "",
            "word_start": "9520",
            "word_stop": "9562"
          }
        },
        {
          "id": "10224",
          "surah_order": "3373",
          "quran_order": "9523",
          "text": "أَنِّى",
          "surah_number": "3",
          "hizb_number": "8",
          "tomon_number": "3",
          "line_order": "5",
          "verse_order": "4",
          "is_last_word": "",
          "is_first_tomon": "",
          "verse": {
            "verse_number": "195",
            "next_verse": "196",
            "previous_verse": "194",
            "sajda": "",
            "is_last_verse": "",
            "is_number_linebreak": "",
            "wakf_end": "",
            "word_start": "9520",
            "word_stop": "9562"
          }
        },
        {
          "id": "10227",
          "surah_order": "3374",
          "quran_order": "9524",
          "text": "لآَ",
          "surah_number": "3",
          "hizb_number": "8",
          "tomon_number": "3",
          "line_order": "6",
          "verse_order": "5",
          "is_last_word": "",
          "is_first_tomon": "",
          "verse": {
            "verse_number": "195",
            "next_verse": "196",
            "previous_verse": "194",
            "sajda": "",
            "is_last_verse": "",
            "is_number_linebreak": "",
            "wakf_end": "",
            "word_start": "9520",
            "word_stop": "9562"
          }
        },
        {
          "id": "10229",
          "surah_order": "3375",
          "quran_order": "9525",
          "text": "ٱُضِيعُ",
          "surah_number": "3",
          "hizb_number": "8",
          "tomon_number": "3",
          "line_order": "7",
          "verse_order": "6",
          "is_last_word": "",
          "is_first_tomon": "",
          "verse": {
            "verse_number": "195",
            "next_verse": "196",
            "previous_verse": "194",
            "sajda": "",
            "is_last_verse": "",
            "is_number_linebreak": "",
            "wakf_end": "",
            "word_start": "9520",
            "word_stop": "9562"
          }
        },
        {
          "id": "10231",
          "surah_order": "3376",
          "quran_order": "9526",
          "text": "عَمَــلَ",
          "surah_number": "3",
          "hizb_number": "8",
          "tomon_number": "3",
          "line_order": "8",
          "verse_order": "7",
          "is_last_word": "",
          "is_first_tomon": "",
          "verse": {
            "verse_number": "195",
            "next_verse": "196",
            "previous_verse": "194",
            "sajda": "",
            "is_last_verse": "",
            "is_number_linebreak": "",
            "wakf_end": "",
            "word_start": "9520",
            "word_stop": "9562"
          }
        },
        {
          "id": "10232",
          "surah_order": "3377",
          "quran_order": "9527",
          "text": "عَــٰمِلٍ",
          "surah_number": "3",
          "hizb_number": "8",
          "tomon_number": "3",
          "line_order": "9",
          "verse_order": "8",
          "is_last_word": "",
          "is_first_tomon": "",
          "verse": {
            "verse_number": "195",
            "next_verse": "196",
            "previous_verse": "194",
            "sajda": "",
            "is_last_verse": "",
            "is_number_linebreak": "",
            "wakf_end": "",
            "word_start": "9520",
            "word_stop": "9562"
          }
        }
      ]
    },
    {
      "line_id": 12,
      "line_number": 13,
      "is_surah_title": "",
      "surah_title": "ءَالِ عِمْرَانَ",
      "surah_title_ar": "آل عمران",
      "surah_title_lt": "Al-Imraan",
      "starts_with_verse_number": "",
      "words": [
        {
          "id": "10238",
          "surah_order": "3378",
          "quran_order": "9528",
          "text": "مِّنكُم",
          "surah_number": "3",
          "hizb_number": "8",
          "tomon_number": "3",
          "line_order": "1",
          "verse_order": "9",
          "is_last_word": "",
          "is_first_tomon": "",
          "verse": {
            "verse_number": "195",
            "next_verse": "196",
            "previous_verse": "194",
            "sajda": "",
            "is_last_verse": "",
            "is_number_linebreak": "",
            "wakf_end": "",
            "word_start": "9520",
            "word_stop": "9562"
          }
        },
        {
          "id": "10271",
          "surah_order": "3379",
          "quran_order": "9529",
          "text": "مِّــن",
          "surah_number": "3",
          "hizb_number": "8",
          "tomon_number": "3",
          "line_order": "2",
          "verse_order": "10",
          "is_last_word": "",
          "is_first_tomon": "",
          "verse": {
            "verse_number": "195",
            "next_verse": "196",
            "previous_verse": "194",
            "sajda": "",
            "is_last_verse": "",
            "is_number_linebreak": "",
            "wakf_end": "",
            "word_start": "9520",
            "word_stop": "9562"
          }
        },
        {
          "id": "10273",
          "surah_order": "3380",
          "quran_order": "9530",
          "text": "ذَكَر۫",
          "surah_number": "3",
          "hizb_number": "8",
          "tomon_number": "3",
          "line_order": "3",
          "verse_order": "11",
          "is_last_word": "",
          "is_first_tomon": "",
          "verse": {
            "verse_number": "195",
            "next_verse": "196",
            "previous_verse": "194",
            "sajda": "",
            "is_last_verse": "",
            "is_number_linebreak": "",
            "wakf_end": "",
            "word_start": "9520",
            "word_stop": "9562"
          }
        },
        {
          "id": "10274",
          "surah_order": "3381",
          "quran_order": "9531",
          "text": "اَوُ",
          "surah_number": "3",
          "hizb_number": "8",
          "tomon_number": "3",
          "line_order": "4",
          "verse_order": "12",
          "is_last_word": "",
          "is_first_tomon": "",
          "verse": {
            "verse_number": "195",
            "next_verse": "196",
            "previous_verse": "194",
            "sajda": "",
            "is_last_verse": "",
            "is_number_linebreak": "",
            "wakf_end": "",
            "word_start": "9520",
            "word_stop": "9562"
          }
        },
        {
          "id": "10276",
          "surah_order": "3382",
          "quran_order": "9532",
          "text": "۷نثۭــيٰؐ",
          "surah_number": "3",
          "hizb_number": "8",
          "tomon_number": "3",
          "line_order": "5",
          "verse_order": "13",
          "is_last_word": "",
          "is_first_tomon": "",
          "verse": {
            "verse_number": "195",
            "next_verse": "196",
            "previous_verse": "194",
            "sajda": "",
            "is_last_verse": "",
            "is_number_linebreak": "",
            "wakf_end": "",
            "word_start": "9520",
            "word_stop": "9562"
          }
        },
        {
          "id": "10278",
          "surah_order": "3383",
          "quran_order": "9533",
          "text": "بَعْضُكُم",
          "surah_number": "3",
          "hizb_number": "8",
          "tomon_number": "3",
          "line_order": "6",
          "verse_order": "14",
          "is_last_word": "",
          "is_first_tomon": "",
          "verse": {
            "verse_number": "195",
            "next_verse": "196",
            "previous_verse": "194",
            "sajda": "",
            "is_last_verse": "",
            "is_number_linebreak": "",
            "wakf_end": "",
            "word_start": "9520",
            "word_stop": "9562"
          }
        },
        {
          "id": "10280",
          "surah_order": "3384",
          "quran_order": "9534",
          "text": "مِّــنۢ",
          "surah_number": "3",
          "hizb_number": "8",
          "tomon_number": "3",
          "line_order": "7",
          "verse_order": "15",
          "is_last_word": "",
          "is_first_tomon": "",
          "verse": {
            "verse_number": "195",
            "next_verse": "196",
            "previous_verse": "194",
            "sajda": "",
            "is_last_verse": "",
            "is_number_linebreak": "",
            "wakf_end": "",
            "word_start": "9520",
            "word_stop": "9562"
          }
        },
        {
          "id": "10283",
          "surah_order": "3385",
          "quran_order": "9535",
          "text": "بَعْضٍؐ",
          "surah_number": "3",
          "hizb_number": "8",
          "tomon_number": "3",
          "line_order": "8",
          "verse_order": "16",
          "is_last_word": "",
          "is_first_tomon": "",
          "verse": {
            "verse_number": "195",
            "next_verse": "196",
            "previous_verse": "194",
            "sajda": "",
            "is_last_verse": "",
            "is_number_linebreak": "",
            "wakf_end": "",
            "word_start": "9520",
            "word_stop": "9562"
          }
        },
        {
          "id": "10285",
          "surah_order": "3386",
          "quran_order": "9536",
          "text": "فَالذِينَ",
          "surah_number": "3",
          "hizb_number": "8",
          "tomon_number": "3",
          "line_order": "9",
          "verse_order": "17",
          "is_last_word": "",
          "is_first_tomon": "",
          "verse": {
            "verse_number": "195",
            "next_verse": "196",
            "previous_verse": "194",
            "sajda": "",
            "is_last_verse": "",
            "is_number_linebreak": "",
            "wakf_end": "",
            "word_start": "9520",
            "word_stop": "9562"
          }
        },
        {
          "id": "10287",
          "surah_order": "3387",
          "quran_order": "9537",
          "text": "هَاجَرُواْ",
          "surah_number": "3",
          "hizb_number": "8",
          "tomon_number": "3",
          "line_order": "10",
          "verse_order": "18",
          "is_last_word": "",
          "is_first_tomon": "",
          "verse": {
            "verse_number": "195",
            "next_verse": "196",
            "previous_verse": "194",
            "sajda": "",
            "is_last_verse": "",
            "is_number_linebreak": "",
            "wakf_end": "",
            "word_start": "9520",
            "word_stop": "9562"
          }
        }
      ]
    },
    {
      "line_id": 13,
      "line_number": 14,
      "is_surah_title": "",
      "surah_title": "ءَالِ عِمْرَانَ",
      "surah_title_ar": "آل عمران",
      "surah_title_lt": "Al-Imraan",
      "starts_with_verse_number": "",
      "words": [
        {
          "id": "10291",
          "surah_order": "3388",
          "quran_order": "9538",
          "text": "وَٱُخْـرۣجُـواْ",
          "surah_number": "3",
          "hizb_number": "8",
          "tomon_number": "3",
          "line_order": "1",
          "verse_order": "19",
          "is_last_word": "",
          "is_first_tomon": "",
          "verse": {
            "verse_number": "195",
            "next_verse": "196",
            "previous_verse": "194",
            "sajda": "",
            "is_last_verse": "",
            "is_number_linebreak": "",
            "wakf_end": "",
            "word_start": "9520",
            "word_stop": "9562"
          }
        },
        {
          "id": "10292",
          "surah_order": "3389",
          "quran_order": "9539",
          "text": "مِـن",
          "surah_number": "3",
          "hizb_number": "8",
          "tomon_number": "3",
          "line_order": "2",
          "verse_order": "20",
          "is_last_word": "",
          "is_first_tomon": "",
          "verse": {
            "verse_number": "195",
            "next_verse": "196",
            "previous_verse": "194",
            "sajda": "",
            "is_last_verse": "",
            "is_number_linebreak": "",
            "wakf_end": "",
            "word_start": "9520",
            "word_stop": "9562"
          }
        },
        {
          "id": "10293",
          "surah_order": "3390",
          "quran_order": "9540",
          "text": "دِيۭــٰرۣهِـمْ",
          "surah_number": "3",
          "hizb_number": "8",
          "tomon_number": "3",
          "line_order": "3",
          "verse_order": "21",
          "is_last_word": "",
          "is_first_tomon": "",
          "verse": {
            "verse_number": "195",
            "next_verse": "196",
            "previous_verse": "194",
            "sajda": "",
            "is_last_verse": "",
            "is_number_linebreak": "",
            "wakf_end": "",
            "word_start": "9520",
            "word_stop": "9562"
          }
        },
        {
          "id": "10294",
          "surah_order": "3391",
          "quran_order": "9541",
          "text": "وَٱُوذُواْ",
          "surah_number": "3",
          "hizb_number": "8",
          "tomon_number": "3",
          "line_order": "4",
          "verse_order": "22",
          "is_last_word": "",
          "is_first_tomon": "",
          "verse": {
            "verse_number": "195",
            "next_verse": "196",
            "previous_verse": "194",
            "sajda": "",
            "is_last_verse": "",
            "is_number_linebreak": "",
            "wakf_end": "",
            "word_start": "9520",
            "word_stop": "9562"
          }
        },
        {
          "id": "10300",
          "surah_order": "3392",
          "quran_order": "9542",
          "text": "فِى",
          "surah_number": "3",
          "hizb_number": "8",
          "tomon_number": "3",
          "line_order": "5",
          "verse_order": "23",
          "is_last_word": "",
          "is_first_tomon": "",
          "verse": {
            "verse_number": "195",
            "next_verse": "196",
            "previous_verse": "194",
            "sajda": "",
            "is_last_verse": "",
            "is_number_linebreak": "",
            "wakf_end": "",
            "word_start": "9520",
            "word_stop": "9562"
          }
        },
        {
          "id": "10302",
          "surah_order": "3393",
          "quran_order": "9543",
          "text": "سَـبِـيـلِى",
          "surah_number": "3",
          "hizb_number": "8",
          "tomon_number": "3",
          "line_order": "6",
          "verse_order": "24",
          "is_last_word": "",
          "is_first_tomon": "",
          "verse": {
            "verse_number": "195",
            "next_verse": "196",
            "previous_verse": "194",
            "sajda": "",
            "is_last_verse": "",
            "is_number_linebreak": "",
            "wakf_end": "",
            "word_start": "9520",
            "word_stop": "9562"
          }
        },
        {
          "id": "10304",
          "surah_order": "3394",
          "quran_order": "9544",
          "text": "وَقَـــٰتَـلُـواْ",
          "surah_number": "3",
          "hizb_number": "8",
          "tomon_number": "3",
          "line_order": "7",
          "verse_order": "25",
          "is_last_word": "",
          "is_first_tomon": "",
          "verse": {
            "verse_number": "195",
            "next_verse": "196",
            "previous_verse": "194",
            "sajda": "",
            "is_last_verse": "",
            "is_number_linebreak": "",
            "wakf_end": "",
            "word_start": "9520",
            "word_stop": "9562"
          }
        },
        {
          "id": "10307",
          "surah_order": "3395",
          "quran_order": "9545",
          "text": "وَقُـتِـلُــواْ",
          "surah_number": "3",
          "hizb_number": "8",
          "tomon_number": "3",
          "line_order": "8",
          "verse_order": "26",
          "is_last_word": "",
          "is_first_tomon": "",
          "verse": {
            "verse_number": "195",
            "next_verse": "196",
            "previous_verse": "194",
            "sajda": "",
            "is_last_verse": "",
            "is_number_linebreak": "",
            "wakf_end": "",
            "word_start": "9520",
            "word_stop": "9562"
          }
        }
      ]
    },
    {
      "line_id": 14,
      "line_number": 15,
      "is_surah_title": "",
      "surah_title": "ءَالِ عِمْرَانَ",
      "surah_title_ar": "آل عمران",
      "surah_title_lt": "Al-Imraan",
      "starts_with_verse_number": "",
      "words": [
        {
          "id": "10311",
          "surah_order": "3396",
          "quran_order": "9546",
          "text": "لُءَكَـفِّـرَنَّ",
          "surah_number": "3",
          "hizb_number": "8",
          "tomon_number": "3",
          "line_order": "9",
          "verse_order": "27",
          "is_last_word": "",
          "is_first_tomon": "",
          "verse": {
            "verse_number": "195",
            "next_verse": "196",
            "previous_verse": "194",
            "sajda": "",
            "is_last_verse": "",
            "is_number_linebreak": "",
            "wakf_end": "",
            "word_start": "9520",
            "word_stop": "9562"
          }
        },
        {
          "id": "10313",
          "surah_order": "3397",
          "quran_order": "9547",
          "text": "عَـنْـهُـمْ",
          "surah_number": "3",
          "hizb_number": "8",
          "tomon_number": "3",
          "line_order": "10",
          "verse_order": "28",
          "is_last_word": "",
          "is_first_tomon": "",
          "verse": {
            "verse_number": "195",
            "next_verse": "196",
            "previous_verse": "194",
            "sajda": "",
            "is_last_verse": "",
            "is_number_linebreak": "",
            "wakf_end": "",
            "word_start": "9520",
            "word_stop": "9562"
          }
        },
        {
          "id": "10319",
          "surah_order": "3398",
          "quran_order": "9548",
          "text": "سَـيِّـَٔـاتِـهِـمْ",
          "surah_number": "3",
          "hizb_number": "8",
          "tomon_number": "3",
          "line_order": "11",
          "verse_order": "29",
          "is_last_word": "",
          "is_first_tomon": "",
          "verse": {
            "verse_number": "195",
            "next_verse": "196",
            "previous_verse": "194",
            "sajda": "",
            "is_last_verse": "",
            "is_number_linebreak": "",
            "wakf_end": "",
            "word_start": "9520",
            "word_stop": "9562"
          }
        },
        {
          "id": "10321",
          "surah_order": "3399",
          "quran_order": "9549",
          "text": "وَلُءَدْخِلَنَّهُمْ",
          "surah_number": "3",
          "hizb_number": "8",
          "tomon_number": "3",
          "line_order": "12",
          "verse_order": "30",
          "is_last_word": "",
          "is_first_tomon": "",
          "verse": {
            "verse_number": "195",
            "next_verse": "196",
            "previous_verse": "194",
            "sajda": "",
            "is_last_verse": "",
            "is_number_linebreak": "",
            "wakf_end": "",
            "word_start": "9520",
            "word_stop": "9562"
          }
        },
        {
          "id": "10323",
          "surah_order": "3400",
          "quran_order": "9550",
          "text": "جَـنَّـــٰــتٍ",
          "surah_number": "3",
          "hizb_number": "8",
          "tomon_number": "3",
          "line_order": "13",
          "verse_order": "31",
          "is_last_word": "",
          "is_first_tomon": "",
          "verse": {
            "verse_number": "195",
            "next_verse": "196",
            "previous_verse": "194",
            "sajda": "",
            "is_last_verse": "",
            "is_number_linebreak": "",
            "wakf_end": "",
            "word_start": "9520",
            "word_stop": "9562"
          }
        },
        {
          "id": "10325",
          "surah_order": "3401",
          "quran_order": "9551",
          "text": "تَجْرۣى",
          "surah_number": "3",
          "hizb_number": "8",
          "tomon_number": "3",
          "line_order": "14",
          "verse_order": "32",
          "is_last_word": "",
          "is_first_tomon": "",
          "verse": {
            "verse_number": "195",
            "next_verse": "196",
            "previous_verse": "194",
            "sajda": "",
            "is_last_verse": "",
            "is_number_linebreak": "",
            "wakf_end": "",
            "word_start": "9520",
            "word_stop": "9562"
          }
        },
        {
          "id": "10327",
          "surah_order": "3402",
          "quran_order": "9552",
          "text": "مِـن",
          "surah_number": "3",
          "hizb_number": "8",
          "tomon_number": "3",
          "line_order": "15",
          "verse_order": "33",
          "is_last_word": "",
          "is_first_tomon": "",
          "verse": {
            "verse_number": "195",
            "next_verse": "196",
            "previous_verse": "194",
            "sajda": "",
            "is_last_verse": "",
            "is_number_linebreak": "",
            "wakf_end": "",
            "word_start": "9520",
            "word_stop": "9562"
          }
        }
      ]
    }
  ]
}